kfp/pipeline_spec/__init__.py
kfp/pipeline_spec/pipeline_spec_pb2.py
kfp_pipeline_spec-2.15.2.dist-info/METADATA
kfp_pipeline_spec-2.15.2.dist-info/WHEEL
kfp_pipeline_spec-2.15.2.dist-info/top_level.txt
kfp_pipeline_spec-2.15.2.dist-info/RECORD
