Metadata-Version: 2.4
Name: kfp-pipeline-spec
Version: 2.15.2
Summary: Kubeflow Pipelines pipeline spec
Home-page: https://github.com/kubeflow/pipelines
Author: google
Author-email: kubeflow-pipelines@google.com
License: Apache 2.0
Requires-Python: >=3.9.0
Requires-Dist: protobuf<7.0,>=6.31.1
Dynamic: author
Dynamic: author-email
Dynamic: home-page
Dynamic: license
Dynamic: requires-dist
Dynamic: requires-python
Dynamic: summary
